checkcorruptedimages
