Metadata-Version: 2.1
Name: checkcorruptedimages
Version: 0.2
Summary: Python3 module to check for corrupted images using "identify" from ImageMagick as underlying mechanism.
Home-page: https://github.com/carlosplanchon/checkcorruptedimages
Author: Carlos A. Planchón
Author-email: bubbledoloresuruguay2@gmail.com
License: GPL3
Download-URL: https://github.com/carlosplanchon/checkcorruptedimages/archive/v0.2.tar.gz
Keywords: check,corrupted,images
Platform: UNKNOWN
Classifier: Intended Audience :: Developers
Classifier: Topic :: Software Development :: Build Tools
Classifier: License :: OSI Approved :: GNU General Public License v3 (GPLv3)
Classifier: Programming Language :: Python :: 3
Classifier: Programming Language :: Python :: 3.4
Classifier: Programming Language :: Python :: 3.5
Classifier: Programming Language :: Python :: 3.6
Classifier: Programming Language :: Python :: 3.7
